LICENSE
README.md
setup.py
hakubooru/__init__.py
hakubooru/caption.py
hakubooru/export.py
hakubooru/logging.py
hakubooru/metainfo.py
hakubooru/source.py
hakubooru/tag_generator.py
hakubooru.egg-info/PKG-INFO
hakubooru.egg-info/SOURCES.txt
hakubooru.egg-info/dependency_links.txt
hakubooru.egg-info/not-zip-safe
hakubooru.egg-info/requires.txt
hakubooru.egg-info/top_level.txt
hakubooru/dataset/__init__.py
hakubooru/dataset/__main__.py
hakubooru/dataset/db.py
hakubooru/dataset/utils.py