Metadata-Version: 2.1
Name: hakubooru
Version: 0.0.3
Summary: Text-image dataset maker for anime-style images
Home-page: https://github.com/KohakuBlueleaf/HakuBooru
Author: Shih-Ying Yeh(KohakuBlueLeaf)
Author-email: apolloyeh0123@gmail.com
License: Apache 2.0
License-File: LICENSE
Requires-Dist: peewee
Requires-Dist: python-dateutil
Requires-Dist: webdataset
Provides-Extra: gui
Requires-Dist: gradio; extra == "gui"
